README.md
setup.py
ga_log/__init__.py
ga_log/handlers.py
ga_log/handlers0000.py
ga_log/log_manager.py
ga_log/monkey_print.py
ga_log/nb_log_config_default.py
ga_log/set_nb_log_config.py
ga_log.egg-info/PKG-INFO
ga_log.egg-info/SOURCES.txt
ga_log.egg-info/dependency_links.txt
ga_log.egg-info/requires.txt
ga_log.egg-info/top_level.txt