Metadata-Version: 2.1
Name: ga-log
Version: 1.2.1
Summary: fork ga_log 
Home-page: UNKNOWN
Author: ziko
Maintainer: ziko
License: BSD License
Keywords: logging,logger,multiprocess file handler,color handler
Platform: all
Classifier: Development Status :: 4 - Beta
Classifier: Operating System :: OS Independent
Classifier: Intended Audience :: Developers
Classifier: License :: OSI Approved :: BSD License
Classifier: Programming Language :: Python
Classifier: Programming Language :: Python :: Implementation
Classifier: Programming Language :: Python :: 3.6
Classifier: Topic :: Software Development :: Libraries
